django_tabbed_changeform_admin/__init__.py
django_tabbed_changeform_admin/admin.py
django_tabbed_changeform_admin/apps.py
django_tabbed_changeform_admin/models.py
django_tabbed_changeform_admin/tests.py
django_tabbed_changeform_admin/views.py
django_tabbed_changeform_admin/migrations/__init__.py
django_tabbed_changeform_admin/static/django-tabbed-changeform-admin/css/django-tabbed-changeform-admin.css
django_tabbed_changeform_admin/static/django-tabbed-changeform-admin/js/django-tabbed-changeform-admin.js
django_tabbed_changeform_admin/templates/admin/change_form.html
django_tabbed_changeform_admin-0.1.9.dist-info/licenses/LICENSE
django_tabbed_changeform_admin-0.1.9.dist-info/METADATA
django_tabbed_changeform_admin-0.1.9.dist-info/WHEEL
django_tabbed_changeform_admin-0.1.9.dist-info/top_level.txt
django_tabbed_changeform_admin-0.1.9.dist-info/RECORD
