Metadata-Version: 2.4
Name: django-tabbed-changeform-admin
Version: 0.1.9
Summary: Group fieldsets or inlinegroups into tabs for django admin's changeform.
Author: rRR0VrFP
Maintainer: rRR0VrFP
License: MIT
Keywords: django admin extentions,django tabbed changeform admin
Classifier: Development Status :: 5 - Production/Stable
Classifier: Intended Audience :: Developers
Classifier: Topic :: Software Development :: Libraries :: Python Modules
Classifier: License :: OSI Approved :: MIT License
Classifier: Programming Language :: Python :: 3
Classifier: Programming Language :: Python :: 3 :: Only
License-File: LICENSE
Requires-Dist: django
Requires-Dist: django-static-jquery-ui>=1.12.1.1
Dynamic: author
Dynamic: classifier
Dynamic: description
Dynamic: description-content-type
Dynamic: keywords
Dynamic: license
Dynamic: license-file
Dynamic: maintainer
Dynamic: requires-dist
Dynamic: summary
